edxml_test_corpus/__init__.py
edxml_test_corpus/tests/3/3.0/3.0.0/conflict/conflicting/input-001.edxml
edxml_test_corpus/tests/3/3.0/3.0.0/conflict/non-conflicting/input-001.edxml
edxml_test_corpus/tests/3/3.0/3.0.0/invalid/event/data-type-base64-corrupted.edxml
edxml_test_corpus/tests/3/3.0/3.0.0/invalid/event/data-type-base64-too-long.edxml
edxml_test_corpus/tests/3/3.0/3.0.0/invalid/event/data-type-bigint-signed-positive.edxml
edxml_test_corpus/tests/3/3.0/3.0.0/invalid/event/data-type-bigint-signed-too-large.edxml
edxml_test_corpus/tests/3/3.0/3.0.0/invalid/event/data-type-bigint-signed-too-small.edxml
edxml_test_corpus/tests/3/3.0/3.0.0/invalid/event/data-type-bigint-signed-zero-negative.edxml
edxml_test_corpus/tests/3/3.0/3.0.0/invalid/event/data-type-bigint-signed-zero-positive.edxml
edxml_test_corpus/tests/3/3.0/3.0.0/invalid/event/data-type-bigint-unsigned-negative.edxml
edxml_test_corpus/tests/3/3.0/3.0.0/invalid/event/data-type-biglint-unsigned-too-large.edxml
edxml_test_corpus/tests/3/3.0/3.0.0/invalid/event/data-type-boolean-numerical.edxml
edxml_test_corpus/tests/3/3.0/3.0.0/invalid/event/data-type-boolean-uppercase.edxml
edxml_test_corpus/tests/3/3.0/3.0.0/invalid/event/data-type-currency-no-padding.edxml
edxml_test_corpus/tests/3/3.0/3.0.0/invalid/event/data-type-currency-nonnumerical.edxml
edxml_test_corpus/tests/3/3.0/3.0.0/invalid/event/data-type-currency-padding.edxml
edxml_test_corpus/tests/3/3.0/3.0.0/invalid/event/data-type-currency-zero-negative.edxml
edxml_test_corpus/tests/3/3.0/3.0.0/invalid/event/data-type-currency-zero-positive.edxml
edxml_test_corpus/tests/3/3.0/3.0.0/invalid/event/data-type-datetime-24:00:00.edxml
edxml_test_corpus/tests/3/3.0/3.0.0/invalid/event/data-type-datetime-missing-decimal.edxml
edxml_test_corpus/tests/3/3.0/3.0.0/invalid/event/data-type-datetime-nonsensical.edxml
edxml_test_corpus/tests/3/3.0/3.0.0/invalid/event/data-type-datetime-without-timezone.edxml
edxml_test_corpus-3.0.1.dist-info/METADATA
edxml_test_corpus-3.0.1.dist-info/WHEEL
edxml_test_corpus-3.0.1.dist-info/top_level.txt
edxml_test_corpus-3.0.1.dist-info/RECORD
