Metadata-Version: 2.1
Name: edxml-test-corpus
Version: 3.0.1
Summary: A collection of portable unit tests for EDXML implementations
Home-page: https://github.com/edxml/test-corpus
Author: Dik Takken
Author-email: dik.takken@edxml.org
Classifier: Programming Language :: Python
Classifier: License :: OSI Approved :: MIT License
Classifier: Operating System :: OS Independent
Classifier: Development Status :: 5 - Production/Stable
Classifier: Topic :: Software Development :: Testing
Classifier: Topic :: Scientific/Engineering :: Artificial Intelligence
